setup.py
devdoo/__init__.py
devdoo/api.py
devdoo/api_db.py
devdoo/broker.py
devdoo/data_rest.py
devdoo/database.py
devdoo/datarest.py
devdoo/datarest_db.py
devdoo/datatypes.py
devdoo/error.py
devdoo/filter.py
devdoo/service.py
devdoo/service_db.py
devdoo/services.py
devdoo/validate.py
packagetest50.egg-info/PKG-INFO
packagetest50.egg-info/SOURCES.txt
packagetest50.egg-info/dependency_links.txt
packagetest50.egg-info/not-zip-safe
packagetest50.egg-info/top_level.txt